SonaWrap/SonaApiError.py
SonaWrap/Wrapper.py
SonaWrap/__init__.py
SonaWrap/schemas/MainMenuInfo.py
SonaWrap/schemas/Schedule.py
SonaWrap/schemas/StudyInfo.py
SonaWrap/schemas/StudyPage.py
SonaWrap/schemas/__init__.py
SonaWrap-0.0.5.dist-info/LICENSE
SonaWrap-0.0.5.dist-info/METADATA
SonaWrap-0.0.5.dist-info/WHEEL
SonaWrap-0.0.5.dist-info/top_level.txt
SonaWrap-0.0.5.dist-info/RECORD
