Metadata-Version: 2.1
Name: SonaWrap
Version: 0.0.5
Summary: A minimal python wrapper for the Sona systems mobile api
Home-page: https://github.com/DavidM42/SonaWrap
Author: David Merz
Author-email: david@merz.dev
License: UNKNOWN
Platform: UNKNOWN
Classifier: Programming Language :: Python :: 3
Classifier: License :: OSI Approved :: MIT License
Classifier: Operating System :: OS Independent
Requires-Python: >=3.6
License-File: LICENSE
